{
  "version": "6",
  "dialect": "sqlite",
  "id": "134f402a-a211-4b64-8195-f80d34e4fe3a",
  "prevId": "00000000-0000-0000-0000-000000000000",
  "tables": {
    "appointments": {
      "name": "appointments",
      "columns": {
        "id": {
          "name": "id",
          "type": "integer",
          "primaryKey": true,
          "notNull": true,
          "autoincrement": true
        },
        "reference_code": {
          "name": "reference_code",
          "type": "text",
          "primaryKey": false,
          "notNull": true,
          "autoincrement": false
        },
        "full_name": {
          "name": "full_name",
          "type": "text",
          "primaryKey": false,
          "notNull": true,
          "autoincrement": false
        },
        "phone": {
          "name": "phone",
          "type": "text",
          "primaryKey": false,
          "notNull": true,
          "autoincrement": false
        },
        "email": {
          "name": "email",
          "type": "text",
          "primaryKey": false,
          "notNull": false,
          "autoincrement": false
        },
        "service_package": {
          "name": "service_package",
          "type": "text",
          "primaryKey": false,
          "notNull": true,
          "autoincrement": false
        },
        "vehicle": {
          "name": "vehicle",
          "type": "text",
          "primaryKey": false,
          "notNull": true,
          "autoincrement": false
        },
        "appointment_date": {
          "name": "appointment_date",
          "type": "text",
          "primaryKey": false,
          "notNull": true,
          "autoincrement": false
        },
        "appointment_time": {
          "name": "appointment_time",
          "type": "text",
          "primaryKey": false,
          "notNull": true,
          "autoincrement": false
        },
        "contact_preference": {
          "name": "contact_preference",
          "type": "text",
          "primaryKey": false,
          "notNull": true,
          "autoincrement": false
        },
        "kvkk_accepted": {
          "name": "kvkk_accepted",
          "type": "integer",
          "primaryKey": false,
          "notNull": true,
          "autoincrement": false
        },
        "marketing_consent": {
          "name": "marketing_consent",
          "type": "integer",
          "primaryKey": false,
          "notNull": true,
          "autoincrement": false,
          "default": false
        },
        "utm_source": {
          "name": "utm_source",
          "type": "text",
          "primaryKey": false,
          "notNull": false,
          "autoincrement": false
        },
        "utm_medium": {
          "name": "utm_medium",
          "type": "text",
          "primaryKey": false,
          "notNull": false,
          "autoincrement": false
        },
        "utm_campaign": {
          "name": "utm_campaign",
          "type": "text",
          "primaryKey": false,
          "notNull": false,
          "autoincrement": false
        },
        "utm_term": {
          "name": "utm_term",
          "type": "text",
          "primaryKey": false,
          "notNull": false,
          "autoincrement": false
        },
        "utm_content": {
          "name": "utm_content",
          "type": "text",
          "primaryKey": false,
          "notNull": false,
          "autoincrement": false
        },
        "status": {
          "name": "status",
          "type": "text",
          "primaryKey": false,
          "notNull": true,
          "autoincrement": false,
          "default": "'pending'"
        },
        "created_at": {
          "name": "created_at",
          "type": "text",
          "primaryKey": false,
          "notNull": true,
          "autoincrement": false,
          "default": "CURRENT_TIMESTAMP"
        }
      },
      "indexes": {
        "appointments_reference_code_unique": {
          "name": "appointments_reference_code_unique",
          "columns": [
            "reference_code"
          ],
          "isUnique": true
        },
        "appointments_phone_created_at_idx": {
          "name": "appointments_phone_created_at_idx",
          "columns": [
            "phone",
            "created_at"
          ],
          "isUnique": false
        },
        "appointments_date_status_idx": {
          "name": "appointments_date_status_idx",
          "columns": [
            "appointment_date",
            "status"
          ],
          "isUnique": false
        }
      },
      "foreignKeys": {},
      "compositePrimaryKeys": {},
      "uniqueConstraints": {},
      "checkConstraints": {
        "appointments_kvkk_accepted_check": {
          "name": "appointments_kvkk_accepted_check",
          "value": "\"appointments\".\"kvkk_accepted\" IN (0, 1)"
        },
        "appointments_marketing_consent_check": {
          "name": "appointments_marketing_consent_check",
          "value": "\"appointments\".\"marketing_consent\" IN (0, 1)"
        },
        "appointments_contact_preference_check": {
          "name": "appointments_contact_preference_check",
          "value": "\"appointments\".\"contact_preference\" IN ('phone', 'whatsapp', 'email', 'sms')"
        },
        "appointments_status_check": {
          "name": "appointments_status_check",
          "value": "\"appointments\".\"status\" IN ('pending', 'confirmed', 'completed', 'cancelled', 'no_show')"
        }
      }
    }
  },
  "views": {},
  "enums": {},
  "_meta": {
    "schemas": {},
    "tables": {},
    "columns": {}
  },
  "internal": {
    "indexes": {}
  }
}